scrapy_drissionpage/__init__.py
scrapy_drissionpage/browser_manager.py
scrapy_drissionpage/downloader.py
scrapy_drissionpage/middleware.py
scrapy_drissionpage/request.py
scrapy_drissionpage/response.py
scrapy_drissionpage/spider.py
scrapy_drissionpage/utils/__init__.py
scrapy_drissionpage/utils/mode_switcher.py
scrapy_drissionpage/utils/selector.py
scrapy_drissionpage-1.0.3.dist-info/LICENSE
scrapy_drissionpage-1.0.3.dist-info/METADATA
scrapy_drissionpage-1.0.3.dist-info/WHEEL
scrapy_drissionpage-1.0.3.dist-info/top_level.txt
scrapy_drissionpage-1.0.3.dist-info/RECORD
