Metadata-Version: 2.1
Name: scrapy-drissionpage
Version: 1.0.3
Summary: 将Scrapy爬虫框架与DrissionPage网页自动化工具进行无缝集成
Home-page: https://github.com/kingking888/scrapy-drissionpage
Author: KingKing888
Author-email: KingKing888 <184108270@qq.com>
License: MIT
Project-URL: Homepage, https://github.com/xyuns-cn/scrapy-drissionpage
Project-URL: Bug Tracker, https://github.com/xyuns-cn/scrapy-drissionpage/issues
Keywords: scrapy,drissionpage,crawler,spider,web scraping,automation,commercial-use,personal-use
Classifier: Programming Language :: Python :: 3
Classifier: Programming Language :: Python :: 3.9
Classifier: Programming Language :: Python :: 3.10
Classifier: Programming Language :: Python :: 3.11
Classifier: License :: OSI Approved :: MIT License
Classifier: Intended Audience :: Developers
Classifier: Development Status :: 4 - Beta
Requires-Python: >=3.9
License-File: LICENSE
Requires-Dist: scrapy>=2.12.0
Requires-Dist: DrissionPage>=4.1.0.18
